odoo/addons/account_invoice_check_total/README.rst
odoo/addons/account_invoice_check_total/__init__.py
odoo/addons/account_invoice_check_total/__manifest__.py
odoo/addons/account_invoice_check_total/i18n/account_invoice_check_total.pot
odoo/addons/account_invoice_check_total/i18n/ar.po
odoo/addons/account_invoice_check_total/i18n/bg.po
odoo/addons/account_invoice_check_total/i18n/bs.po
odoo/addons/account_invoice_check_total/i18n/ca.po
odoo/addons/account_invoice_check_total/i18n/cs.po
odoo/addons/account_invoice_check_total/i18n/de.po
odoo/addons/account_invoice_check_total/i18n/el_GR.po
odoo/addons/account_invoice_check_total/i18n/en_GB.po
odoo/addons/account_invoice_check_total/i18n/es.po
odoo/addons/account_invoice_check_total/i18n/es_CR.po
odoo/addons/account_invoice_check_total/i18n/es_EC.po
odoo/addons/account_invoice_check_total/i18n/es_ES.po
odoo/addons/account_invoice_check_total/i18n/es_MX.po
odoo/addons/account_invoice_check_total/i18n/et.po
odoo/addons/account_invoice_check_total/i18n/fi.po
odoo/addons/account_invoice_check_total/i18n/fr.po
odoo/addons/account_invoice_check_total/i18n/fr_CA.po
odoo/addons/account_invoice_check_total/i18n/fr_CH.po
odoo/addons/account_invoice_check_total/i18n/gl.po
odoo/addons/account_invoice_check_total/i18n/hr.po
odoo/addons/account_invoice_check_total/i18n/hr_HR.po
odoo/addons/account_invoice_check_total/i18n/hu.po
odoo/addons/account_invoice_check_total/i18n/id.po
odoo/addons/account_invoice_check_total/i18n/it.po
odoo/addons/account_invoice_check_total/i18n/ja.po
odoo/addons/account_invoice_check_total/i18n/lt.po
odoo/addons/account_invoice_check_total/i18n/mk.po
odoo/addons/account_invoice_check_total/i18n/mn.po
odoo/addons/account_invoice_check_total/i18n/nb.po
odoo/addons/account_invoice_check_total/i18n/nb_NO.po
odoo/addons/account_invoice_check_total/i18n/nl.po
odoo/addons/account_invoice_check_total/i18n/nl_BE.po
odoo/addons/account_invoice_check_total/i18n/nl_NL.po
odoo_addon_account_invoice_check_total-18.0.1.0.0.4.dist-info/METADATA
odoo_addon_account_invoice_check_total-18.0.1.0.0.4.dist-info/WHEEL
odoo_addon_account_invoice_check_total-18.0.1.0.0.4.dist-info/top_level.txt
odoo_addon_account_invoice_check_total-18.0.1.0.0.4.dist-info/RECORD
