Metadata-Version: 2.1
Name: odoo-addon-account_invoice_check_total
Version: 18.0.1.0.0.4
Requires-Python: >=3.10
Requires-Dist: odoo==18.0.*
Summary: Check if the verification total is equal to the bill's total
Home-page: https://github.com/OCA/account-invoicing
License: AGPL-3
Author: Acsone SA/NV, Odoo Community Association (OCA)
Author-email: support@odoo-community.org
Classifier: Programming Language :: Python
Classifier: Framework :: Odoo
Classifier: Framework :: Odoo :: 18.0
Classifier: License :: OSI Approved :: GNU Affero General Public License v3
